f3utils/__init__.py
f3utils/date_eval.py
f3utils/dict_tools.py
f3utils/loopthread.py
f3utils/options.py
f3utils/pool.py
f3utils/service_meta.py
f3utils/time_lc.py
f3utils-0.11.dist-info/DESCRIPTION.rst
f3utils-0.11.dist-info/METADATA
f3utils-0.11.dist-info/RECORD
f3utils-0.11.dist-info/WHEEL
f3utils-0.11.dist-info/metadata.json
f3utils-0.11.dist-info/top_level.txt
