Metadata-Version: 2.0
Name: f3utils
Version: 0.11
Summary: Utilities from the F3 ERP suite
Home-page: UNKNOWN
Author: Panos Christeas
Author-email: xrg@pefnos.com
License: LGPLv3
Keywords: f3,python
Platform: Platform Independent
Classifier: Development Status :: 4 - Beta
Classifier: Intended Audience :: Developers
Classifier: Operating System :: OS Independent
Classifier: Programming Language :: Python
Classifier: Topic :: Software Development :: Libraries :: Python Modules
Classifier: Topic :: System :: Filesystems
